{
    "server":"0.0.0.0",
    "server_ipv6":"[::]",
    "local_address":"127.0.0.1",
    "local_port":1080,
    "port_password" : {
		"7000": "abcdef123",
		"7001": "abcdef123",
		"7002": "abcdef123",
		"7003": "abcdef123",
		"7004": "abcdef123",
		"7005": "abcdef123",
		"7006": "abcdef123",
		"7007": "abcdef123",
		"7008": "abcdef123",
		"7009": "abcdef123",
		"7010": "abcdef123",
		"7011": "abcdef123",
		"7012": "abcdef123",
		"7013": "abcdef123",
		"7014": "abcdef123",
		"7015": "abcdef123",
		"7016": "abcdef123",
		"7017": "abcdef123",
		"7018": "abcdef123",
		"7019": "abcdef123",
		"7020": "abcdef123",
		"7021": "abcdef123",
		"7022": "abcdef123",
		"7023": "abcdef123",
		"7024": "abcdef123",
		"7025": "abcdef123",
		"7026": "abcdef123",
		"7027": "abcdef123",
		"7028": "abcdef123",
		"7029": "abcdef123",
		"7030": "abcdef123"
    },
    "timeout":120,
    "method":"chacha20",
    "protocol":"auth_sha1_v4_compatible",
    "protocol_param":"",
    "obfs":"http_simple_compatible",
    "obfs_param":"",
    "redirect":"",
    "dns_ipv6":false,
    "fast_open":false,
    "workers":1
}
